{
 "based_on": "creation",
 "chart_name": "Packages reported",
 "chart_type": "Count",
 "creation": "2020-08-08 00:39:39.760282",
 "custom_options": "",
 "docstatus": 0,
 "doctype": "Dashboard Chart",
 "document_type": "Package",
 "dynamic_filters_json": "[]",
 "filters_json": "[]",
 "group_by_type": "Count",
 "idx": 0,
 "is_public": 1,
 "is_standard": 1,
 "last_synced_on": "2020-11-22 10:47:17.836105",
 "modified": "2020-11-22 10:49:01.619147",
 "modified_by": "Administrator",
 "module": "Package Management",
 "name": "Packages reported",
 "number_of_groups": 0,
 "owner": "Administrator",
 "source": "",
 "time_interval": "Daily",
 "timeseries": 1,
 "timespan": "Last Month",
 "type": "Bar",
 "use_report_chart": 0,
 "value_based_on": "",
 "y_axis": []
}